gui/__init__.py
gui/two_networked_pumps/__init__.py
gui/two_networked_pumps/two_networked_gui.py
gui/two_networked_pumps/two_networked_pump_gui_design.py
new_era/__init__.py
new_era/__version__.py
new_era/peristaltic_pump.py
new_era/peristaltic_pump_network.py
new_era/utils.py
newera/__init__.py
newera/new_era.py
new_era-2.2.3.dist-info/LICENSE
new_era-2.2.3.dist-info/METADATA
new_era-2.2.3.dist-info/WHEEL
new_era-2.2.3.dist-info/top_level.txt
new_era-2.2.3.dist-info/RECORD
