Metadata-Version: 2.1
Name: new-era
Version: 2.2.3
Summary: An unofficial library to control New Era pumps. We are not affliated with New Era.
Home-page: https://gitlab.com/heingroup/new_era
Author: Veronica Lai // Hein Group
Author-email: 
License: UNKNOWN
Platform: UNKNOWN
Requires-Python: >=3.6
Requires-Dist: pyserial
